CHANGES
COPYING
MANIFEST.in
README
dbuck
dbuck.1
hostgrep
hostgrep.1
hostlist
hostlist.1
hostlist.py
pshbak
pshbak.1
python-hostlist.spec
setup.py
python_hostlist.egg-info/PKG-INFO
python_hostlist.egg-info/SOURCES.txt
python_hostlist.egg-info/dependency_links.txt
python_hostlist.egg-info/top_level.txt
test/test_hostlist.py