Metadata-Version: 2.1
Name: python_hostlist
Version: 2.3.0
Summary: Python module for hostlist handling
Home-page: http://www.nsc.liu.se/~kent/python-hostlist/
Author: Kent Engström
Author-email: kent@nsc.liu.se
License: GPL2+
Classifier: Development Status :: 5 - Production/Stable
Classifier: Intended Audience :: Science/Research
Classifier: Intended Audience :: System Administrators
Classifier: License :: OSI Approved :: GNU General Public License (GPL)
Classifier: Topic :: System :: Clustering
Classifier: Topic :: System :: Systems Administration
Classifier: Programming Language :: Python :: 3
License-File: COPYING
